oliverj_utils/__init__.py
oliverj_utils/timing.py
oliverj_util-0.0.6.dist-info/LICENSE
oliverj_util-0.0.6.dist-info/METADATA
oliverj_util-0.0.6.dist-info/WHEEL
oliverj_util-0.0.6.dist-info/top_level.txt
oliverj_util-0.0.6.dist-info/RECORD
