Metadata-Version: 2.1
Name: oliverj-util
Version: 0.0.6
Summary: A utility package
Home-page: https://pypi.org/project/oliverj-util
Author: Olliejohnson
Author-email: contact@oliverj.io
License: MIT
Requires-Python: >=3.8
License-File: LICENSE
